README.md
setup.py
tserror/__init__.py
tserror/metrics.py
tserror.egg-info/PKG-INFO
tserror.egg-info/SOURCES.txt
tserror.egg-info/dependency_links.txt
tserror.egg-info/requires.txt
tserror.egg-info/top_level.txt